callingcardstools/Alignment/AlignmentTagger.py
callingcardstools/Alignment/SummaryParser.py
callingcardstools/Alignment/__init__.py
callingcardstools/Alignment/mammals/Qbed.py
callingcardstools/Alignment/mammals/__init__.py
callingcardstools/Alignment/mammals/combine_qc.py
callingcardstools/Alignment/mammals/process_alignments.py
callingcardstools/Alignment/yeast/__init__.py
callingcardstools/Alignment/yeast/legacy_makeccf.py
callingcardstools/Alignment/yeast/process_alignments.py
callingcardstools/Analysis/__init__.py
callingcardstools/Analysis/yeast/__init__.py
callingcardstools/Analysis/yeast/chipexo_promoter_sig.py
callingcardstools/Analysis/yeast/find_min_responsive.py
callingcardstools/Analysis/yeast/rank_response.py
callingcardstools/Analysis/yeast/read_in_data.py
callingcardstools/BarcodeParser/BarcodeParser.py
callingcardstools/BarcodeParser/__init__.py
callingcardstools/BarcodeParser/mammals/BarcodeQcCounter.py
callingcardstools/BarcodeParser/mammals/__init__.py
callingcardstools/BarcodeParser/yeast/BarcodeQcCounter.py
callingcardstools/BarcodeParser/yeast/__init__.py
callingcardstools/BarcodeParser/yeast/barcode_table_to_json.py
callingcardstools/BarcodeParser/yeast/combine_qc.py
callingcardstools/PeakCalling/__init__.py
callingcardstools/PeakCalling/yeast/__init__.py
callingcardstools/PeakCalling/yeast/call_peaks.py
callingcardstools/PeakCalling/yeast/enrichment_vectorized.py
callingcardstools/PeakCalling/yeast/hypergeom_pval_vectorized.py
callingcardstools/PeakCalling/yeast/poisson_pval_vectorized.py
callingcardstools/PeakCalling/yeast/read_in_data.py
callingcardstools/QC/StatusFlags.py
callingcardstools/QC/__init__.py
callingcardstools/QC/create_status_coder.py
callingcardstools/Reads/ReadParser.py
callingcardstools/Reads/__init__.py
callingcardstools/Reads/legacy_split_fastq.py
callingcardstools/Reads/split_fastq.py
callingcardstools/Resources/Resources.py
callingcardstools/Resources/__init__.py
callingcardstools/Resources/mammals/__init__.py
callingcardstools-1.8.1.dist-info/LICENSE
callingcardstools-1.8.1.dist-info/METADATA
callingcardstools-1.8.1.dist-info/WHEEL
callingcardstools-1.8.1.dist-info/entry_points.txt
callingcardstools-1.8.1.dist-info/RECORD
