Metadata-Version: 2.1
Name: callingCardsTools
Version: 1.8.1
Summary: A collection of objects and functions to work with calling cards sequencing tools
Home-page: https://cmatkhan.github.io/callingCardsTools/
License: MIT
Author: chase mateusiak
Author-email: chase.mateusiak@gmail.com
Requires-Python: >=3.9
Classifier: License :: OSI Approved :: MIT License
Classifier: Programming Language :: Python :: 3
Classifier: Programming Language :: Python :: 3.9
Classifier: Programming Language :: Python :: 3.10
Classifier: Programming Language :: Python :: 3.11
Classifier: Programming Language :: Python :: 3.12
Classifier: Programming Language :: Python :: 3.13
Requires-Dist: biopython (>=1.81,<2.0)
Requires-Dist: edlib (>=1.3.9,<2.0.0)
Requires-Dist: intervaltree (>=3.1.0,<4.0.0)
Requires-Dist: numpy (>=1.24.3,<2.0.0)
Requires-Dist: pandas (>=1.5.3,<2.0.0)
Requires-Dist: pyranges (>=0.0.129,<0.0.130)
Requires-Dist: pysam (>=0.19.1,<0.20.0)
Requires-Dist: scipy (>=1.11.4,<2.0.0)
Project-URL: Documentation, https://cmatkhan.github.io/callingCardsTools/
Project-URL: Repository, https://github.com/cmatKhan/callingCardsTools
